scikit_hep_sizeof/__init__.py
scikit_hep_sizeof-0.1.0.dist-info/LICENSE
scikit_hep_sizeof-0.1.0.dist-info/METADATA
scikit_hep_sizeof-0.1.0.dist-info/WHEEL
scikit_hep_sizeof-0.1.0.dist-info/entry_points.txt
scikit_hep_sizeof-0.1.0.dist-info/top_level.txt
scikit_hep_sizeof-0.1.0.dist-info/RECORD
